hedera_proto/__init__.py
hedera_proto/account_balance_file_pb2.py
hedera_proto/basic_types_pb2.py
hedera_proto/consensus_create_topic_pb2.py
hedera_proto/consensus_delete_topic_pb2.py
hedera_proto/consensus_get_topic_info_pb2.py
hedera_proto/consensus_service_pb2.py
hedera_proto/consensus_service_pb2_grpc.py
hedera_proto/consensus_submit_message_pb2.py
hedera_proto/consensus_topic_info_pb2.py
hedera_proto/consensus_update_topic_pb2.py
hedera_proto/contract_action_pb2.py
hedera_proto/contract_bytecode_pb2.py
hedera_proto/contract_call_local_pb2.py
hedera_proto/contract_call_pb2.py
hedera_proto/contract_create_pb2.py
hedera_proto/contract_delete_pb2.py
hedera_proto/contract_get_bytecode_pb2.py
hedera_proto/contract_get_info_pb2.py
hedera_proto/contract_get_records_pb2.py
hedera_proto/contract_state_change_pb2.py
hedera_proto/contract_types_pb2.py
hedera_proto/contract_update_pb2.py
hedera_proto/crypto_add_live_hash_pb2.py
hedera_proto/crypto_approve_allowance_pb2.py
hedera_proto/crypto_create_pb2.py
hedera_proto/crypto_delete_allowance_pb2.py
hedera_proto/crypto_delete_live_hash_pb2.py
hedera_proto/crypto_delete_pb2.py
hedera_proto/crypto_get_account_balance_pb2.py
hedera_proto/crypto_get_account_records_pb2.py
hedera_proto/crypto_get_info_pb2.py
hedera_proto/crypto_get_live_hash_pb2.py
hedera_proto/crypto_get_stakers_pb2.py
hedera_proto/crypto_service_pb2.py
hedera_proto/crypto_service_pb2_grpc.py
hedera_proto/crypto_transfer_pb2.py
hedera_proto/crypto_update_pb2.py
hedera_proto/custom_fees_pb2.py
hedera_proto/duration_pb2.py
hedera_proto/ethereum_transaction_pb2.py
hedera_proto/exchange_rate_pb2.py
hedera_proto/file_append_pb2.py
hedera_proto/file_create_pb2.py
hedera_proto/file_delete_pb2.py
hedera_proto/file_get_contents_pb2.py
hedera_proto/file_get_info_pb2.py
hedera_proto/file_service_pb2.py
hedera_proto/file_service_pb2_grpc.py
hedera_proto/file_update_pb2.py
hedera_proto/freeze_pb2.py
hedera_proto/freeze_service_pb2.py
hedera_proto/freeze_service_pb2_grpc.py
hedera_proto-0.49.1.dist-info/LICENSE
hedera_proto-0.49.1.dist-info/METADATA
hedera_proto-0.49.1.dist-info/WHEEL
hedera_proto-0.49.1.dist-info/top_level.txt
hedera_proto-0.49.1.dist-info/RECORD
