Metadata-Version: 2.1
Name: hedera-proto
Version: 0.49.1
Summary: Hedera Protobufs
Home-page: https://github.com/HbarStudio/hedera-protobufs-python
Author: Wensheng Wang
Author-email: wenshengwang@gmail.com
Project-URL: Bug Tracker, https://github.com/HbarStudio/hedera-protobufs-python/issues
Classifier: Programming Language :: Python :: 3
Classifier: License :: OSI Approved :: Apache Software License
Classifier: Operating System :: OS Independent
Requires-Python: >=3.8
License-File: LICENSE
Requires-Dist: grpcio >=1.59.3
